{
  "version": "5.4.1",
  "flags": {},
  "shapes": [
    {
      "label": "table",
      "points": [
        [
          122.65060240963874,
          1049.638554216865
        ],
        [
          1240.7228915662558,
          312.2891566265059
        ]
      ],
      "group_id": null,
      "description": "",
      "shape_type": "rectangle",
      "flags": {},
      "mask": null
    },
    {
      "label": "ref",
      "points": [
        [
          580.4819277108431,
          780.9638554216868
        ],
        [
          828.6746987951807,
          546.0240963855422
        ]
      ],
      "group_id": null,
      "description": "",
      "shape_type": "rectangle",
      "flags": {},
      "mask": null
    },
    {
      "label": "object",
      "points": [
        [
          687.7108433734948,
          758.072289156626
        ],
        [
          806.9879518072286,
          641.2048192771085
        ]
      ],
      "group_id": null,
      "description": "",
      "shape_type": "rectangle",
      "flags": {},
      "mask": null
    },
    {
      "label": "object",
      "points": [
        [
          306.98795180722885,
          554.4578313253012
        ],
        [
          444.3373493975904,
          672.5301204819277
        ]
      ],
      "group_id": null,
      "description": "",
      "shape_type": "rectangle",
      "flags": {},
      "mask": null
    },
    {
      "label": "object",
      "points": [
        [
          587.7108433734929,
          542.4096385542169
        ],
        [
          708.1927710843378,
          658.0722891566268
        ]
      ],
      "group_id": null,
      "description": "",
      "shape_type": "rectangle",
      "flags": {},
      "mask": null
    }
  ],
  "imagePath": "WIN_20240405_14_15_55_Pro.jpg",
  "imageData": null,
  "imageHeight": 1080,
  "imageWidth": 1920
}