{
  "version": "5.4.1",
  "flags": {},
  "shapes": [
    {
      "label": "table",
      "points": [
        [
          629.8795180722889,
          1059.2771084337346
        ],
        [
          1744.33734939759,
          333.9759036144577
        ]
      ],
      "group_id": null,
      "description": "",
      "shape_type": "rectangle",
      "flags": {},
      "mask": null
    },
    {
      "label": "ref",
      "points": [
        [
          1067.2289156626507,
          789.3975903614459
        ],
        [
          1304.578313253012,
          559.277108433735
        ]
      ],
      "group_id": null,
      "description": "",
      "shape_type": "rectangle",
      "flags": {},
      "mask": null
    },
    {
      "label": "object",
      "points": [
        [
          1078.0722891566263,
          664.0963855421687
        ],
        [
          1187.7108433734938,
          552.0481927710845
        ]
      ],
      "group_id": null,
      "description": "",
      "shape_type": "rectangle",
      "flags": {},
      "mask": null
    }
  ],
  "imagePath": "WIN_20240404_15_43_53_Pro.jpg",
  "imageData": null,
  "imageHeight": 1080,
  "imageWidth": 1920
}